mental_api_client/__init__.py
mental_api_client/api_types.py
mental_api_client/base.py
mental_api_client/client.py
mental_api_client/exceptions.py
mental_api_client-0.1.5.dist-info/METADATA
mental_api_client-0.1.5.dist-info/WHEEL
mental_api_client-0.1.5.dist-info/top_level.txt
mental_api_client-0.1.5.dist-info/RECORD
