Metadata-Version: 2.1
Name: mental-api-client
Version: 0.1.5
Summary: Client for team mental api
Home-page: https://github.com/hqdem/team_mental_pyclient
Author: Ilya Demidov
Author-email: iademidov@edu.hse.ru
License: BSD 2-clause
Classifier: Programming Language :: Python :: 3
Requires-Dist: certifi ==2023.7.22
Requires-Dist: charset-normalizer ==3.3.2
Requires-Dist: idna ==3.4
Requires-Dist: requests ==2.31.0
Requires-Dist: urllib3 ==2.0.7
